eda_kit/__init__.py
eda_kit/auto_eda.py
eda_kit/eda_analyzer.py
eda_kit/missing_value_handler.py
eda_kit/report_generator.py
quickeda_kit-0.1.1.dist-info/licenses/LICENSE
quickeda_kit-0.1.1.dist-info/METADATA
quickeda_kit-0.1.1.dist-info/WHEEL
quickeda_kit-0.1.1.dist-info/top_level.txt
quickeda_kit-0.1.1.dist-info/RECORD
