Metadata-Version: 2.4
Name: quickeda-kit
Version: 0.1.1
Summary: A completely automatic EDA (Exploratory Data Analysis) library for Python
Home-page: https://github.com/ashishali/quickeda_kit
Author: Ashish
Author-email: ashishbearyy@gmail.com
Project-URL: Bug Reports, https://github.com/ashishali/quickeda_kit/issues
Project-URL: Source, https://github.com/ashishali/quickeda_kit
Project-URL: Documentation, https://github.com/ashishali/quickeda_kit#readme
Keywords: data-science,eda,exploratory-data-analysis,machine-learning,data-analysis,pandas,automation
Classifier: Development Status :: 3 - Alpha
Classifier: Intended Audience :: Developers
Classifier: Intended Audience :: Science/Research
Classifier: Topic :: Scientific/Engineering
Classifier: Topic :: Software Development :: Libraries :: Python Modules
Classifier: License :: OSI Approved :: MIT License
Classifier: Operating System :: OS Independent
Classifier: Programming Language :: Python :: 3
Classifier: Programming Language :: Python :: 3.7
Classifier: Programming Language :: Python :: 3.8
Classifier: Programming Language :: Python :: 3.9
Classifier: Programming Language :: Python :: 3.10
Classifier: Programming Language :: Python :: 3.11
Classifier: Programming Language :: Python :: 3.12
Requires-Python: >=3.7
License-File: LICENSE
Requires-Dist: pandas>=1.3.0
Requires-Dist: numpy>=1.21.0
Requires-Dist: matplotlib>=3.4.0
Requires-Dist: seaborn>=0.11.0
Requires-Dist: scipy>=1.7.0
Requires-Dist: scikit-learn>=1.0.0
Dynamic: author
Dynamic: author-email
Dynamic: classifier
Dynamic: description
Dynamic: description-content-type
Dynamic: home-page
Dynamic: keywords
Dynamic: license-file
Dynamic: project-url
Dynamic: requires-dist
Dynamic: requires-python
Dynamic: summary
